scrapy_crawl_once/__init__.py
scrapy_crawl_once/middlewares.py
scrapy_crawl_once-0.1.1.dist-info/DESCRIPTION.rst
scrapy_crawl_once-0.1.1.dist-info/METADATA
scrapy_crawl_once-0.1.1.dist-info/RECORD
scrapy_crawl_once-0.1.1.dist-info/WHEEL
scrapy_crawl_once-0.1.1.dist-info/metadata.json
scrapy_crawl_once-0.1.1.dist-info/top_level.txt
